{
  "transaction_type": [
    {
      "name": "deposit",
      "label": "Depósito"
    },
    {
      "name": "withdrawal",
      "label": "Saque"
    }
  ],
  "request_status": [
    {
      "name": "pending",
      "label": "Pendente"
    },
    {
      "name": "approved",
      "label": "Aprovado"
    },
    {
      "name": "denied",
      "label": "Negado"
    }
  ],
  "match_result": [
    {
      "name": "win",
      "label": "Ganhou"
    },
    {
      "name": "loss",
      "label": "Perdeu"
    }
  ],
  "account_type": [
    {
      "name": "beginner",
      "label": "Iniciante"
    },
    {
      "name": "intermediary",
      "label": "Intermediário"
    },
    {
      "name": "advanced",
      "label": "Avançado"
    }
  ],
  "user_status": [
    {
      "name": "active",
      "label": "Ativo"
    },
    {
      "name": "inactive",
      "label": "Inativo"
    },
    {
      "name": "banned",
      "label": "Banido"
    }
  ],
  "user_type": [
    {
      "name": "administrator",
      "label": "Administrador"
    },
    {
      "name": "player",
      "label": "Jogador"
    },
    {
      "name": "affiliate",
      "label": "Afiliado"
    },
    {
      "name": "demo",
      "label": "Demo"
    }
  ]
}
